{
  "ignoredLinks": [
    {
      "source": "about/our-future-goals/index.html",
      "target": "/en/about/president-message/"
    },
    {
      "source": "en/about/future/index.html",
      "target": "/en/about/president-message/"
    },
    {
      "source": "intro-of-cwts/vision_and_mission_statement_chn/index.html",
      "target": "/zh/about/vision-and-mission/"
    },
    {
      "source": "mission/index.html",
      "target": "/zh/about/vision-and-mission/"
    }
  ],
  "ignoredAssets": [
    "_astro/newsletter-2017A.BfvHrXqK.pdf",
    "_astro/newsletter-2017B.B4pYQ9Hc.pdf",
    "_astro/newsletter-2017C.D_2JKPeJ.pdf",
    "_astro/newsletter-2017D.GEl5go9Z.pdf",
    "_astro/newsletter-2018A.CXN7CyIJ.pdf",
    "_astro/newsletter-2018B.BDHUWXNR.pdf",
    "_astro/newsletter-2018C.Dh-sQ1LK.pdf",
    "_astro/newsletter-2018D.B7nWSFta.pdf",
    "_astro/newsletter-2019A.DftC1lPg.pdf",
    "_astro/newsletter-2019B.DSz2kluA.pdf",
    "_astro/newsletter-2019C.jP3TS-4D.pdf",
    "_astro/newsletter-2019D.D5ivEA0x.pdf",
    "_astro/newsletter-2020A.B9_rhCWL.pdf",
    "_astro/newsletter-2020B.CFe3ruti.pdf",
    "_astro/newsletter-2020C.Ca8RJAki.pdf",
    "_astro/newsletter-2020D.BihwRnI-.pdf",
    "_astro/newsletter-2021A.CYQ4Dypg.pdf",
    "_astro/newsletter-2021B.DyvSdNze.pdf",
    "_astro/newsletter-2021C.Bet-6MuC.pdf",
    "_astro/newsletter-2021D.KKe-R-9i.pdf",
    "_astro/newsletter-2022A.P0aNmAxL.pdf",
    "_astro/newsletter-2022B.C081O5mk.pdf",
    "_astro/newsletter-2022C._VxXLuco.pdf",
    "_astro/newsletter-2022D.DyVjhbw0.pdf",
    "_astro/newsletter-2023A.BSNstiQl.pdf",
    "_astro/newsletter-2023B.C9O_yzWf.pdf",
    "_astro/newsletter-2023C.BcXge6Gi.pdf",
    "_astro/newsletter-2024A.ZiKl5l1T.pdf",
    "_astro/newsletter-2024B.Ble8T9OI.pdf",
    "_astro/newsletter-2024C.CmuSXGFQ.pdf",
    "_astro/newsletter-2025A.DBSdtA9V.pdf",
    "_astro/newsletter-2025B.BvELzpBS.pdf",
    "_astro/newsletter-2025C.BPK1jGEv.pdf",
    "_astro/newsletter-2026A.CgInv_4g.pdf",
    "android-chrome-192x192.png",
    "android-chrome-512x512.png",
    "docs/admissions/Application-Form-DMin_111422.pdf",
    "docs/admissions/Application-Form-Masters-040924.pdf",
    "docs/admissions/Application-Form-ThM_111422.pdf",
    "docs/admissions/DMin-Handbook-2020-2021-Chinese.pdf",
    "docs/admissions/DMin助學金申請表-簡_tbf.pdf",
    "docs/admissions/Health-History-Form-revised.pdf",
    "docs/admissions/I-20-Application-Form-DMin-fillable.pdf",
    "docs/admissions/Recommendation-Form2020Fall-revised.pdf",
    "docs/admissions/Registration-Form2022-Spring.pdf",
    "docs/admissions/foreignAppPolicy.pdf",
    "docs/babc/點擊瀏覽講員介紹工作坊介紹.pdf",
    "docs/jobs/2022-08-23-CEC-中文牧師尋牧廣告-Andrew-Lo.pdf",
    "docs/jobs/2022-09-05-Portland-CCMA-Pastoral-Search-Andrew-Lo.pdf",
    "docs/jobs/2022-09-06-ACCC-Childrens-Director-Position.pdf",
    "docs/jobs/2022-10-10-Advertisement-for-GCC-Andrew-Lo.pdf",
    "docs/jobs/2022-10-20-First Chinese Church of Christ in Hawaii.pdf",
    "docs/jobs/2022-10-23-TriCity Chinese Baptist Church.pdf",
    "docs/jobs/2022-10-26-SFCBC-Senior-Pastor-–-Bilingual-English-Cantonese.pdf",
    "docs/jobs/2022-10-27-Youth-Pastor-TCC-Job-Description.pdf",
    "docs/jobs/2022-11-01-FEC-Glendale-Mandarin-Assistant-Minister-AD-Andrew-Lo.pdf",
    "docs/jobs/2022-11-04-DCCC-Pastor-Search.pdf",
    "docs/jobs/2022-12-02-聘牧-拉斯維加斯生命河靈糧堂-Andrew-Lo.pdf",
    "docs/jobs/2023-01-05-紐約華人播道會誠聘資料-Andrew-Lo.pdf",
    "docs/jobs/2023-01-31-Boston-Chinese-Evangelical-Church-Job-Open.pdf",
    "docs/jobs/2023-03-20-Cantonese-Pastor-RespQua.pdf",
    "docs/jobs/2023-04-06-Chinese-Christian-Church-and-Center-English-Track-Next-Generation-Director-Job-Description-Andrew-Lo.pdf",
    "docs/jobs/2023-05-09-Children Minister Job  Description v 03-23 - Andrew Lo.pdf",
    "docs/jobs/2023-05-09-Children Minister Job Description - Andrew Lo.pdf",
    "docs/jobs/2023-05-09-Director of Children Ministry Job  Description v 03-23 - Andrew Lo.pdf",
    "docs/jobs/2023-05-09-基督教門諾會救恩堂教會 -传道人 - Andrew Lo.pdf",
    "docs/jobs/2023-05-09-基督教門諾會救恩堂教會 -牧师 - Andrew Lo.pdf",
    "docs/jobs/2023-06-23-Knoxville Chinese Christian Church 牧師.pdf",
    "docs/jobs/2023-07-24 Denton Chinese Church pastoral search.pdf",
    "docs/jobs/2023-08-11-Logos軟體徵才.pdf",
    "docs/jobs/2023-09-11-Hawaii Chinese Baptist Church.pdf",
    "docs/jobs/2023-09-13-El Cerrito Chinese Christian Church Pastor.pdf",
    "docs/jobs/2023-09-18-Faith Hope Love Chinese Church.pdf",
    "docs/jobs/2023-09-19-Arise Church.pdf",
    "docs/jobs/2023-10-02-Knoxville Chinese Christian Church.pdf",
    "docs/jobs/2023-11-13-Long Island Abundant Life Church.pdf",
    "docs/jobs/2023-11-21-Home of Christ Morgan Hill.pdf",
    "docs/jobs/2023-12-12-Chinese Christian Church of NJ.pdf",
    "docs/jobs/2024-02-16-ROLCCGH-Chinese Pastor.pdf",
    "docs/jobs/2024-02-17-ROLCCGH-Youth Director.pdf",
    "docs/jobs/2024-02-28-CCCNC-College Ministry Director.pdf",
    "docs/jobs/2024-03-06-Boston Chinese Evangelical Church.pdf",
    "docs/jobs/2024-04-15-RCCA-Youth Minister.pdf",
    "docs/jobs/2024-04-16-NHCCW-Youth Pastor.pdf",
    "docs/jobs/2024-04-22-BCEC-Senior Pastor.pdf",
    "docs/jobs/2024-05-29-CCBC-Chinese Pastor.pdf",
    "docs/jobs/2024-06-01-SSJCBC-Chinese Pastor.pdf",
    "docs/jobs/2024-06-14-EFCP-PT Youth.pdf",
    "docs/jobs/2024-06-24-Grace Chinese Baptist-Chinese Pastor.pdf",
    "docs/jobs/2024-06-27-PSC Mandarin Assoc Pastor.pdf",
    "docs/jobs/2024-07-24-CBC English Pastor.pdf",
    "docs/jobs/2024-07-29-FCGC Chinese Pastor.pdf",
    "docs/jobs/2024-08-30-OCMJireh Mandarin Pastor.pdf",
    "docs/jobs/2024-12-05-MCCC Pastoral Position.pdf",
    "docs/jobs/2024-12-10-First Ithaca Chinese Christian Church-Chinese Pastor.pdf",
    "docs/jobs/2024-12-18-ACC-Children's Minister.pdf",
    "docs/jobs/2025-02-12-CCCJ-Positions.pdf",
    "docs/jobs/2025-02-18-Las Vegas CBC-Chinese Pastor.pdf",
    "docs/jobs/2025-02-19-SBCGC-Senior Pastor.pdf",
    "docs/jobs/2025-02-20-ClearwaterCCC-Chinese Pastor.pdf",
    "docs/jobs/2025-02-21-SFCLC-Chinese Pastor.pdf",
    "docs/jobs/2025-03-16-Sunset Church-Assistant Cantonese Pastor.pdf",
    "docs/jobs/2025-03-17-KCCC-EM Pastor.pdf",
    "docs/ministry-institute/SoulCare-PersonalitySeminar.png",
    "docs/ministry-institute/SoulCare-SF.jpg",
    "docs/ministry-institute/soul-child-psyc.jpg",
    "docs/ministry-institute/soul-emotions-spiritual.png",
    "images/babc/2022/Lu.jpg",
    "images/babc/2022/Rons-Headshot-1.jpg",
    "images/babc/2022/Ted-hah-1.jpg",
    "images/babc/2022/劉效宏.png",
    "images/babc/2022/吳羅瑜-1.png",
    "images/babc/2022/孔毅-1.jpg",
    "images/babc/2022/孫慈俠-1.jpg",
    "images/babc/2022/葉裕波-1.jpg",
    "images/babc/2022/鄭立新-1.jpg",
    "images/babc/2024/Stephen Chen.jpg",
    "images/babc/2024/劉慈謙.jpg",
    "images/babc/2024/劉浩宇.jpg",
    "images/babc/2024/孫慈俠.jpg",
    "images/babc/2024/孫艾苓.jpg",
    "images/babc/2024/林有洧.jpg",
    "images/babc/2024/羅一強.jpg",
    "images/babc/2024/蔡明謀.jpg",
    "images/babc/2024/鄒永恆.jpg",
    "images/babc/2024/錢澄.jpg",
    "images/babc/2024/陳聲漢.jpg",
    "images/babc/2025/Alice-Ott.jpg",
    "images/babc/2025/Craig-Ott.jpg",
    "images/babc/2025/Daniel-Low.jpg",
    "images/babc/2025/John-Talbott.jpg",
    "images/babc/2025/John-Wang.jpg",
    "images/babc/2025/Justin-Talbott.jpg",
    "images/babc/2025/Kenneth-Goh.jpg",
    "images/babc/2025/Lawrence-Ko.jpg",
    "images/babc/2025/Melody-Goh.JPG",
    "images/babc/2025/Nick-Gee.jpg",
    "images/babc/2025/Nick-Wu.jpg",
    "images/babc/2025/Peter-Tie.jpg",
    "images/bg-vision-and-mission.jpg",
    "images/covers/about.cover.jpg",
    "images/covers/about/accreditation.cover.jpg",
    "images/covers/about/administration.cover.jpg",
    "images/covers/about/board.cover.jpg",
    "images/covers/about/ctlc.cover.jpg",
    "images/covers/about/effectiveness-statement.cover.jpg",
    "images/covers/about/feature.cover.jpg",
    "images/covers/about/future.cover.jpg",
    "images/covers/about/history.cover.jpg",
    "images/covers/about/statement-of-faith.cover.jpg",
    "images/covers/about/vision-and-mission.cover.jpg",
    "images/covers/academic.cover.jpg",
    "images/covers/academic/catalog.cover.jpg",
    "images/covers/academic/course-schedule.cover.jpg",
    "images/covers/academic/degrees-programs.cover.jpg",
    "images/covers/academic/faculty.cover.jpg",
    "images/covers/academic/library.cover.jpg",
    "images/covers/academic/online-program.cover.jpg",
    "images/covers/academic/registration-notice.cover.jpg",
    "images/covers/academic/regulations.cover.jpg",
    "images/covers/admissions.cover.jpg",
    "images/covers/admissions/application-procedure.cover.jpg",
    "images/covers/admissions/international.cover.jpg",
    "images/covers/admissions/tuition-scholarship.cover.jpg",
    "images/covers/contact.cover.jpg",
    "images/covers/default.cover.jpg",
    "images/covers/degrees-programs/certificate-in-servant-leadership.cover.jpg",
    "images/covers/degrees-programs/certificate-of-children-ministry.cover.jpg",
    "images/covers/degrees-programs/certificate-of-children-ministry.thumbnail.jpg",
    "images/covers/degrees-programs/certificate-of-evangelism-ministry.cover.jpg",
    "images/covers/degrees-programs/certificate-of-evangelism-ministry.thumbnail.jpg",
    "images/covers/degrees-programs/certificate-of-family-ministry.cover.jpg",
    "images/covers/degrees-programs/certificate-of-family-ministry.thumbnail.jpg",
    "images/covers/degrees-programs/diploma-in-church-leadership.cover.jpg",
    "images/covers/degrees-programs/diploma-in-church-leadership.thumbnail.jpg",
    "images/covers/degrees-programs/diploma-of-christian-studies.cover.jpg",
    "images/covers/degrees-programs/doctor.cover.jpg",
    "images/covers/degrees-programs/master.cover.jpg",
    "images/covers/donation.cover.jpg",
    "images/covers/ministry-institute.cover.jpg",
    "images/covers/ministry-institute/about.cover.jpg",
    "images/covers/ministry-institute/application.cover.jpg",
    "images/covers/ministry-institute/catalog.cover.jpg",
    "images/covers/ministry-institute/courses.cover.jpg",
    "images/covers/ministry-institute/recording.cover.jpg",
    "images/covers/ministry-institute/resources.cover.jpg",
    "images/covers/news-events.cover.jpg",
    "images/covers/news-events/bay-area-bible-convention.cover.jpg",
    "images/covers/news-events/forum.cover.jpg",
    "images/covers/news-events/newsletter.cover.jpg",
    "images/covers/news-events/servant-leadership.cover.jpg",
    "images/covers/news-events/tan-lectureship.cover.jpg",
    "images/covers/student-life.cover.jpg",
    "images/covers/student-life/assembly.cover.jpg",
    "images/covers/student-life/calendar.cover.jpg",
    "images/covers/student-life/dormitory.cover.jpg",
    "images/covers/student-life/job-posting.cover.jpg",
    "images/covers/student-life/prayer.cover.jpg",
    "images/covers/student-life/prayer.thumbnail.jpg",
    "images/degrees-programs/default-cover.jpg",
    "images/dr-tsai-signature.jpg",
    "images/faculty/dr-chen.jpg",
    "images/faculty/rev-dr-lu.jpg",
    "images/icons/speaker.svg",
    "images/why-us/diversity.svg",
    "images/why-us/location.svg",
    "images/why-us/scholarship.svg",
    "images/why-us/strong-faculty.svg",
    "logo.svg",
    "mstile-144x144.png",
    "mstile-150x150.png",
    "mstile-310x150.png",
    "mstile-310x310.png",
    "mstile-70x70.png"
  ]
}